{
  "updated_at": "2026-06-04T00:21:52.042752",
  "currency_name": "спасибки",
  "month": "2026-06",
  "top_month": [
    {
      "user_id": "818748106",
      "name": "Костя",
      "amount": 57
    },
    {
      "user_id": "5311640125",
      "name": "Matvei",
      "amount": 25
    },
    {
      "user_id": "747818163",
      "name": "Анна",
      "amount": 25
    }
  ],
  "users": {
    "818748106": {
      "name": "Костя",
      "balance": 62,
      "received_month": 57,
      "received_total": 62
    },
    "5311640125": {
      "name": "Matvei",
      "balance": 0,
      "received_month": 25,
      "received_total": 25
    },
    "747818163": {
      "name": "Анна",
      "balance": 25,
      "received_month": 25,
      "received_total": 25
    }
  },
  "admin_ids": [
    "818748106"
  ],
  "products": [
    {
      "id": 1,
      "name": "Тестовый товар",
      "description": "Описание тестового товара",
      "price": 100,
      "active": true
    }
  ],
  "stats": {
    "users_count": 3,
    "transactions_count": 6,
    "total_given_month": 107
  }
}